{
    "creditos": [
      {
        "id": 1,
        "archivo": "clientes_credito.xml",
        "expedicion": "02/08/20",
        "calidad" : "90%",
        "estatus" : "Finalizado",
        "finalizacion":" 02/08/21",
        "usuario": "@mmencia"
      },
      {
        "id": 2,
        "archivo": "clientes_contrato.xml",
        "expedicion": "12/08/20",
        "calidad" : "55%",
        "estatus" : "En proceso",
        "finalizacion":" 12/08/21",
        "usuario": "@mmencia"
      },
      {
        "id": 3,
        "archivo": "clientes_credito.xml",
        "expedicion": "24/08/20",
        "calidad" : "87%",
        "estatus" : "Finalizado",
        "finalizacion":" 24/08/21",
        "usuario": "@agarcia"
      },
      {
        "id": 4,
        "archivo": "contrato-cliente.xml",
        "expedicion": "30/08/20",
        "calidad" : "88%",
        "estatus" : "Rechazado",
        "finalizacion":" 30/08/21",
        "usuario": "@pgomez"
      }
    ]
  }